{
  "state": {
    "week": 4,
    "leg": 4,
    "season": "2025",
    "season_type": "regular",
    "league_season": "2025",
    "previous_season": "2024",
    "season_start_date": "2025-09-04",
    "display_week": 4,
    "league_create_season": "2025",
    "season_has_scores": true
  },
  "league": {
    "name": "Family Fantasy Football",
    "status": "in_season",
    "metadata": {
      "auto_continue": "on",
      "keeper_deadline": "0"
    },
    "settings": {
      "best_ball": 0,
      "last_report": 3,
      "waiver_budget": 100,
      "disable_adds": 0,
      "divisions": 2,
      "capacity_override": 0,
      "waiver_bid_min": 0,
      "taxi_deadline": 0,
      "draft_rounds": 3,
      "reserve_allow_na": 0,
      "start_week": 1,
      "playoff_seed_type": 0,
      "playoff_teams": 6,
      "veto_votes_needed": 5,
      "num_teams": 10,
      "daily_waivers_hour": 0,
      "playoff_type": 0,
      "taxi_slots": 0,
      "last_scored_leg": 3,
      "daily_waivers_days": 5461,
      "playoff_week_start": 15,
      "waiver_clear_days": 2,
      "reserve_allow_doubtful": 0,
      "commissioner_direct_invite": 0,
      "veto_auto_poll": 0,
      "reserve_allow_dnr": 0,
      "taxi_allow_vets": 0,
      "waiver_day_of_week": 2,
      "playoff_round_type": 0,
      "reserve_allow_out": 0,
      "reserve_allow_sus": 0,
      "veto_show_votes": 0,
      "trade_deadline": 11,
      "taxi_years": 0,
      "daily_waivers": 0,
      "disable_trades": 0,
      "pick_trading": 1,
      "type": 0,
      "max_keepers": 1,
      "waiver_type": 0,
      "league_average_match": 0,
      "trade_review_days": 2,
      "bench_lock": 0,
      "offseason_adds": 0,
      "leg": 4,
      "reserve_slots": 2,
      "reserve_allow_cov": 0,
      "daily_waivers_last_ran": 24
    },
    "avatar": null,
    "company_id": null,
    "last_message_id": "1277853076115439616",
    "sport": "nfl",
    "shard": 368,
    "season": "2025",
    "season_type": "regular",
    "scoring_settings": {
      "sack": 1,
      "qb_hit": 0,
      "fgm_40_49": 4,
      "bonus_rec_te": 0,
      "fgm_yds": 0,
      "def_forced_punts": 0,
      "bonus_rec_yd_100": 0,
      "bonus_rush_yd_100": 0,
      "pass_int": -2,
      "fgmiss_50p": 0,
      "pts_allow_0": 5,
      "bonus_pass_yd_400": 0,
      "pass_2pt": 2,
      "rec_0_4": 0,
      "yds_allow_450_499": -5,
      "blk_kick_ret_yd": 0,
      "st_td": 6,
      "def_pr_yd": 0,
      "rec_30_39": 0,
      "sack_yd": 0,
      "fgm_yds_over_30": 0,
      "rec_td": 6,
      "yds_allow_400_449": -3,
      "tkl_ast": 0,
      "rec_20_29": 0,
      "fgm_30_39": 3,
      "xpmiss": -1,
      "rush_td_50p": 0,
      "rush_td": 6,
      "def_kr_yd": 0,
      "bonus_fd_wr": 0,
      "pts_allow": 0,
      "def_4_and_stop": 0,
      "fg_ret_yd": 0,
      "yds_allow_550p": -7,
      "pass_td_40p": 0,
      "def_st_tkl_solo": 0,
      "yds_allow_350_399": -1,
      "fgm": 0,
      "idp_sack_yd": 0,
      "bonus_rush_rec_yd_100": 0,
      "rec_2pt": 2,
      "bonus_pass_cmp_25": 0,
      "rush_fd": 0,
      "pass_int_td": 0,
      "int_ret_yd": 0,
      "pass_att": 0,
      "st_fum_rec": 1,
      "fgmiss": -1,
      "bonus_def_fum_td_50p": 0,
      "ff": 1,
      "bonus_sack_2p": 0,
      "fgmiss_30_39": 0,
      "rec": 1,
      "yds_allow_200_299": 2,
      "pts_allow_14_20": 1,
      "def_2pt": 0,
      "fgm_0_19": 3,
      "idp_pass_def_3p": 0,
      "int": 2,
      "def_st_fum_rec": 1,
      "fum_lost": -2,
      "pts_allow_1_6": 4,
      "rec_fd": 0,
      "kr_yd": 0,
      "fgmiss_20_29": 0,
      "rush_att": 0,
      "st_tkl_solo": 0,
      "yds_allow": 0,
      "rec_5_9": 0,
      "fgm_20_29": 3,
      "yds_allow_500_549": -6,
      "pts_allow_21_27": 0,
      "bonus_rec_wr": 0,
      "bonus_pass_yd_300": 0,
      "xpm": 1,
      "pass_td_50p": 0,
      "pass_sack": 0,
      "rec_40p": 0,
      "def_3_and_out": 0,
      "fgmiss_0_19": 0,
      "pass_cmp": 0,
      "tkl_loss": 0,
      "rush_2pt": 2,
      "def_pass_def": 0,
      "yds_allow_300_349": 0,
      "fum_rec": 2,
      "rec_10_19": 0,
      "bonus_rec_yd_200": 0,
      "def_st_td": 6,
      "tkl": 0,
      "pass_cmp_40p": 0,
      "fgm_50p": 5,
      "bonus_tkl_10p": 0,
      "def_td": 6,
      "pass_fd": 0,
      "rec_td_40p": 0,
      "bonus_rush_yd_200": 0,
      "safe": 2,
      "pass_yd": 0.05,
      "fgmiss_40_49": 0,
      "rec_td_50p": 0,
      "blk_kick": 2,
      "pass_td": 6,
      "tkl_solo": 0,
      "bonus_rush_att_20": 0,
      "yds_allow_100_199": 3,
      "bonus_def_int_td_50p": 0,
      "bonus_fd_qb": 0,
      "rush_yd": 0.1,
      "yds_allow_0_100": 5,
      "bonus_rec_rb": 0,
      "rush_40p": 0,
      "pr_yd": 0,
      "fum": 0,
      "pts_allow_28_34": -1,
      "pts_allow_35p": -4,
      "bonus_rush_rec_yd_200": 0,
      "fum_rec_td": 6,
      "rec_yd": 0.1,
      "rush_td_40p": 0,
      "bonus_fd_te": 0,
      "bonus_fd_rb": 0,
      "fum_ret_yd": 0,
      "def_st_ff": 1,
      "pass_inc": 0,
      "pts_allow_7_13": 3,
      "st_ff": 1
    },
    "last_author_avatar": null,
    "last_author_display_name": "sys",
    "last_author_id": "166666666666666666",
    "last_author_is_bot": true,
    "last_message_attachment": null,
    "last_message_text_map": null,
    "last_message_time": 1759026424009,
    "last_pinned_message_id": null,
    "draft_id": "1257465328837861377",
    "last_read_id": null,
    "league_id": "1257465328837861376",
    "previous_league_id": "1120808251861479424",
    "group_id": null,
    "roster_positions": [
      "QB",
      "RB",
      "RB",
      "WR",
      "WR",
      "TE",
      "FLEX",
      "K",
      "DEF",
      "BN",
      "BN",
      "BN",
      "BN",
      "BN"
    ],
    "bracket_id": null,
    "bracket_overrides_id": null,
    "loser_bracket_id": null,
    "loser_bracket_overrides_id": null,
    "total_rosters": 10
  },
  "users": [
    {
      "avatar": "2e1c3f5d039ee5984f551ac05ce6474d",
      "display_name": "zackwalker",
      "is_bot": false,
      "is_owner": true,
      "league_id": "1257465328837861376",
      "metadata": {
        "allow_pn": "on",
        "avatar": "https://sleepercdn.com/uploads/3a842bb47c11494031e5764cc0ccc067.jpg",
        "league_report_pn": "off",
        "mascot_message": "off",
        "mention_pn": "on",
        "player_like_pn": "off",
        "player_nickname_update": "off",
        "team_name": "Bye Bye ryan",
        "team_name_update": "off",
        "trade_block_pn": "off",
        "transaction_commissioner": "off",
        "transaction_free_agent": "off",
        "transaction_trade": "off",
        "transaction_waiver": "off",
        "user_message_pn": "on"
      },
      "settings": null,
      "user_id": "350720035741827072"
    },
    {
      "avatar": "b987f66667023baafadeb2051a35b7c1",
      "display_name": "AndrewBrewer18",
      "is_bot": false,
      "is_owner": false,
      "league_id": "1257465328837861376",
      "metadata": {
        "allow_pn": "on",
        "mention_pn": "on",
        "team_name": "Nice Tets"
      },
      "settings": null,
      "user_id": "561736455764434944"
    },
    {
      "avatar": "82aec8e811b839b8ec25d7b458afd57b",
      "display_name": "lucy2010",
      "is_bot": false,
      "is_owner": false,
      "league_id": "1257465328837861376",
      "metadata": {
        "allow_pn": "on",
        "allow_sms": "on",
        "mention_pn": "on",
        "team_name": "Kissmybutker"
      },
      "settings": null,
      "user_id": "867237162704388096"
    },
    {
      "avatar": "b3338675f635c2c1f42b469621d38ec6",
      "display_name": "rebdub",
      "is_bot": false,
      "is_owner": false,
      "league_id": "1257465328837861376",
      "metadata": {
        "allow_pn": "on",
        "allow_sms": "on",
        "avatar": "https://sleepercdn.com/uploads/94cedc0e2fc6cc865390f744eb06f445.jpg",
        "league_report_pn": "off",
        "mascot_message": "off",
        "mention_pn": "on",
        "player_like_pn": "off",
        "player_nickname_update": "off",
        "team_name": "Living on Lashes & Luck",
        "team_name_update": "off",
        "trade_block_pn": "off",
        "transaction_commissioner": "off",
        "transaction_free_agent": "off",
        "transaction_trade": "off",
        "transaction_waiver": "off",
        "user_message_pn": "off"
      },
      "settings": null,
      "user_id": "874531798980489216"
    },
    {
      "avatar": "c23ebb80664369ed28228bc3a50cbf1b",
      "display_name": "SugarX2",
      "is_bot": false,
      "is_owner": false,
      "league_id": "1257465328837861376",
      "metadata": {
        "allow_pn": "on",
        "allow_sms": "on",
        "avatar": "https://sleepercdn.com/uploads/634e9ac2d657b921c6aa279285a12d11.jpg",
        "league_report_pn": "off",
        "mascot_message": "off",
        "mention_pn": "on",
        "player_like_pn": "off",
        "player_nickname_update": "off",
        "team_name": "SugarX2",
        "team_name_update": "off",
        "trade_block_pn": "off",
        "transaction_commissioner": "on",
        "transaction_free_agent": "on",
        "transaction_trade": "off",
        "transaction_waiver": "on",
        "user_message_pn": "off"
      },
      "settings": null,
      "user_id": "1120813678284066816"
    },
    {
      "avatar": "15d7cf259bc30eab8f6120f45f652fb6",
      "display_name": "molliebrewer",
      "is_bot": false,
      "is_owner": false,
      "league_id": "1257465328837861376",
      "metadata": {
        "allow_pn": "on",
        "avatar": "https://sleepercdn.com/uploads/492d4340d8e2b2f488ab0fdc16544b5f.jpg",
        "mention_pn": "on",
        "team_name": "Ivy League"
      },
      "settings": null,
      "user_id": "1120848933724553216"
    },
    {
      "avatar": "82aec8e811b839b8ec25d7b458afd57b",
      "display_name": "Rwalker2001",
      "is_bot": false,
      "is_owner": false,
      "league_id": "1257465328837861376",
      "metadata": {
        "allow_pn": "on",
        "avatar": "https://sleepercdn.com/uploads/0a49e204c650c36051bac597832d8d17.jpg",
        "mention_pn": "on",
        "team_name": "Ambulancechasers"
      },
      "settings": null,
      "user_id": "1120919091793031168"
    },
    {
      "avatar": "82aec8e811b839b8ec25d7b458afd57b",
      "display_name": "Hopefulhandfull",
      "is_bot": false,
      "is_owner": false,
      "league_id": "1257465328837861376",
      "metadata": {
        "allow_pn": "on",
        "avatar": "https://sleepercdn.com/uploads/6193575aa7c286289cc6a56b78fc2486.jpg",
        "mention_pn": "on",
        "team_name": "The Stevie Wonders"
      },
      "settings": null,
      "user_id": "1121913753026531328"
    },
    {
      "avatar": "f82a8122d7564fdff3a38c796499c72a",
      "display_name": "631to405",
      "is_bot": false,
      "is_owner": false,
      "league_id": "1257465328837861376",
      "metadata": {
        "allow_pn": "on",
        "allow_sms": "on",
        "avatar": "https://sleepercdn.com/uploads/20f76fb53dea7cbb8cb0a8ab97e90255.jpg",
        "mention_pn": "on",
        "team_name": "Da’Quan Scuffles "
      },
      "settings": null,
      "user_id": "1122498641165492224"
    },
    {
      "avatar": "e7af4deab0289b4f5505646424895246",
      "display_name": "ewpollard",
      "is_bot": false,
      "is_owner": false,
      "league_id": "1257465328837861376",
      "metadata": {
        "allow_pn": "on",
        "allow_sms": "on",
        "avatar": "https://sleepercdn.com/uploads/b561439e1aabf86a4769f24ec7b64a23.jpg",
        "league_report_pn": "on",
        "mascot_message": "off",
        "mention_pn": "on",
        "player_like_pn": "on",
        "player_nickname_update": "off",
        "team_name": "Aaron Rodgers’ Brain Rot",
        "team_name_update": "off",
        "trade_block_pn": "on",
        "transaction_commissioner": "off",
        "transaction_free_agent": "off",
        "transaction_trade": "on",
        "transaction_waiver": "off",
        "user_message_pn": "on"
      },
      "settings": null,
      "user_id": "1122734732875354112"
    }
  ],
  "rosters": [
    {
      "co_owners": null,
      "keepers": null,
      "league_id": "1257465328837861376",
      "metadata": {
        "allow_pn_inactive_starters": "on",
        "allow_pn_player_injury_status": "on",
        "allow_pn_scoring": "on",
        "p_nick_1234": "Loser Wilson",
        "record": "WLL",
        "restrict_pn_scoring_starters_only": "on",
        "streak": "2L"
      },
      "owner_id": "350720035741827072",
      "player_map": null,
      "players": [
        "10236",
        "11577",
        "11620",
        "2747",
        "3321",
        "5844",
        "5859",
        "6797",
        "6801",
        "8137",
        "8151",
        "9509",
        "GB"
      ],
      "reserve": null,
      "roster_id": 1,
      "settings": {
        "division": 1,
        "fpts": 363,
        "fpts_against": 404,
        "fpts_against_decimal": 90,
        "fpts_decimal": 10,
        "losses": 2,
        "ppts": 427,
        "ppts_decimal": 60,
        "ties": 0,
        "total_moves": 0,
        "waiver_budget_used": 0,
        "waiver_position": 7,
        "wins": 1
      },
      "starters": [
        "6797",
        "9509",
        "8151",
        "11620",
        "8137",
        "10236",
        "5859",
        "2747",
        "GB"
      ],
      "taxi": null
    },
    {
      "co_owners": null,
      "keepers": null,
      "league_id": "1257465328837861376",
      "metadata": {
        "record": "LWL",
        "streak": "1L"
      },
      "owner_id": "561736455764434944",
      "player_map": null,
      "players": [
        "11632",
        "11638",
        "11655",
        "12512",
        "12526",
        "12527",
        "3163",
        "4195",
        "4981",
        "5045",
        "7569",
        "9224",
        "9484",
        "ATL"
      ],
      "reserve": null,
      "roster_id": 2,
      "settings": {
        "division": 1,
        "fpts": 336,
        "fpts_against": 386,
        "fpts_against_decimal": 20,
        "fpts_decimal": 15,
        "losses": 2,
        "ppts": 397,
        "ppts_decimal": 95,
        "ties": 0,
        "total_moves": 0,
        "waiver_budget_used": 0,
        "waiver_position": 1,
        "wins": 1
      },
      "starters": [
        "3163",
        "12527",
        "12512",
        "11632",
        "7569",
        "9484",
        "12526",
        "4195",
        "ATL"
      ],
      "taxi": null
    },
    {
      "co_owners": null,
      "keepers": null,
      "league_id": "1257465328837861376",
      "metadata": {
        "allow_pn_inactive_starters": "on",
        "allow_pn_player_injury_status": "on",
        "allow_pn_scoring": "on",
        "record": "LWW",
        "restrict_pn_scoring_starters_only": "on",
        "streak": "2W"
      },
      "owner_id": "1120813678284066816",
      "player_map": null,
      "players": [
        "10222",
        "11539",
        "11563",
        "12481",
        "2133",
        "5850",
        "5947",
        "6904",
        "7002",
        "7049",
        "7564",
        "8155",
        "9488",
        "9754",
        "DEN"
      ],
      "reserve": [
        "10222"
      ],
      "roster_id": 3,
      "settings": {
        "division": 2,
        "fpts": 381,
        "fpts_against": 337,
        "fpts_against_decimal": 25,
        "fpts_decimal": 25,
        "losses": 1,
        "ppts": 424,
        "ppts_decimal": 60,
        "ties": 0,
        "total_moves": 0,
        "waiver_budget_used": 0,
        "waiver_position": 9,
        "wins": 2
      },
      "starters": [
        "6904",
        "12481",
        "5850",
        "7564",
        "9488",
        "7002",
        "2133",
        "11539",
        "DEN"
      ],
      "taxi": null
    },
    {
      "co_owners": null,
      "keepers": null,
      "league_id": "1257465328837861376",
      "metadata": {
        "record": "WWW",
        "streak": "3W"
      },
      "owner_id": "1120848933724553216",
      "player_map": null,
      "players": [
        "11560",
        "3451",
        "4046",
        "4199",
        "5012",
        "5846",
        "5872",
        "7547",
        "7553",
        "7594",
        "8150",
        "9493",
        "9997",
        "MIN"
      ],
      "reserve": null,
      "roster_id": 4,
      "settings": {
        "division": 2,
        "fpts": 415,
        "fpts_against": 315,
        "fpts_against_decimal": 95,
        "fpts_decimal": 45,
        "losses": 0,
        "ppts": 523,
        "ppts_decimal": 15,
        "ties": 0,
        "total_moves": 0,
        "waiver_budget_used": 0,
        "waiver_position": 2,
        "wins": 3
      },
      "starters": [
        "11560",
        "8150",
        "7594",
        "9493",
        "7547",
        "7553",
        "9997",
        "3451",
        "MIN"
      ],
      "taxi": null
    },
    {
      "co_owners": null,
      "keepers": null,
      "league_id": "1257465328837861376",
      "metadata": {
        "record": "WWW",
        "streak": "3W"
      },
      "owner_id": "1120919091793031168",
      "player_map": null,
      "players": [
        "11533",
        "11589",
        "11631",
        "12506",
        "4035",
        "4984",
        "5849",
        "5892",
        "6786",
        "7588",
        "8130",
        "8144",
        "8408",
        "TB"
      ],
      "reserve": null,
      "roster_id": 5,
      "settings": {
        "division": 1,
        "fpts": 398,
        "fpts_against": 339,
        "fpts_against_decimal": 35,
        "fpts_decimal": 25,
        "losses": 0,
        "ppts": 439,
        "ppts_decimal": 65,
        "ties": 0,
        "total_moves": 0,
        "waiver_budget_used": 0,
        "waiver_position": 6,
        "wins": 3
      },
      "starters": [
        "4984",
        "8408",
        "7588",
        "8144",
        "11631",
        "8130",
        "12506",
        "11533",
        "TB"
      ],
      "taxi": null
    },
    {
      "co_owners": null,
      "keepers": null,
      "league_id": "1257465328837861376",
      "metadata": {
        "allow_pn_inactive_starters": "on",
        "allow_pn_player_injury_status": "on",
        "allow_pn_scoring": "off",
        "record": "LLL",
        "restrict_pn_scoring_starters_only": "on",
        "streak": "3L"
      },
      "owner_id": "874531798980489216",
      "player_map": null,
      "players": [
        "10213",
        "10859",
        "11564",
        "11584",
        "11628",
        "12489",
        "17",
        "3198",
        "4033",
        "4983",
        "6111",
        "6770",
        "6819",
        "8228",
        "PHI"
      ],
      "reserve": [
        "6770"
      ],
      "roster_id": 6,
      "settings": {
        "division": 2,
        "fpts": 286,
        "fpts_against": 366,
        "fpts_against_decimal": 35,
        "fpts_decimal": 95,
        "losses": 3,
        "ppts": 373,
        "ppts_decimal": 75,
        "ties": 0,
        "total_moves": 0,
        "waiver_budget_used": 0,
        "waiver_position": 8,
        "wins": 0
      },
      "starters": [
        "11564",
        "3198",
        "11584",
        "6819",
        "4983",
        "10859",
        "10213",
        "17",
        "PHI"
      ],
      "taxi": null
    },
    {
      "co_owners": null,
      "keepers": null,
      "league_id": "1257465328837861376",
      "metadata": {
        "record": "LLL",
        "streak": "3L"
      },
      "owner_id": "867237162704388096",
      "player_map": null,
      "players": [
        "12501",
        "1466",
        "1479",
        "3294",
        "4034",
        "4039",
        "4892",
        "5848",
        "5927",
        "5967",
        "7543",
        "8110",
        "8259",
        "KC"
      ],
      "reserve": null,
      "roster_id": 7,
      "settings": {
        "division": 2,
        "fpts": 347,
        "fpts_against": 413,
        "fpts_against_decimal": 65,
        "fpts_decimal": 95,
        "losses": 3,
        "ppts": 393,
        "ppts_decimal": 15,
        "ties": 0,
        "total_moves": 0,
        "waiver_budget_used": 0,
        "waiver_position": 4,
        "wins": 0
      },
      "starters": [
        "4892",
        "4034",
        "7543",
        "5848",
        "1479",
        "8110",
        "4039",
        "8259",
        "KC"
      ],
      "taxi": null
    },
    {
      "co_owners": null,
      "keepers": null,
      "league_id": "1257465328837861376",
      "metadata": {
        "record": "WLW",
        "streak": "1W"
      },
      "owner_id": "1121913753026531328",
      "player_map": null,
      "players": [
        "12504",
        "12533",
        "1339",
        "4037",
        "4217",
        "4227",
        "4866",
        "4881",
        "7525",
        "7526",
        "8138",
        "8146",
        "8183",
        "ARI"
      ],
      "reserve": null,
      "roster_id": 8,
      "settings": {
        "division": 1,
        "fpts": 410,
        "fpts_against": 407,
        "fpts_against_decimal": 25,
        "fpts_decimal": 0,
        "losses": 1,
        "ppts": 445,
        "ppts_decimal": 50,
        "ties": 0,
        "total_moves": 0,
        "waiver_budget_used": 0,
        "waiver_position": 5,
        "wins": 2
      },
      "starters": [
        "4881",
        "4866",
        "8138",
        "8146",
        "7525",
        "1339",
        "7526",
        "4227",
        "ARI"
      ],
      "taxi": null
    },
    {
      "co_owners": null,
      "keepers": null,
      "league_id": "1257465328837861376",
      "metadata": {
        "allow_pn_inactive_starters": "on",
        "allow_pn_player_injury_status": "on",
        "allow_pn_scoring": "off",
        "record": "WLW",
        "restrict_pn_scoring_starters_only": "on",
        "streak": "1W"
      },
      "owner_id": "1122734732875354112",
      "player_map": null,
      "players": [
        "12507",
        "12514",
        "12518",
        "12529",
        "12530",
        "12711",
        "2216",
        "6804",
        "6813",
        "8112",
        "8148",
        "9221",
        "9494",
        "DET"
      ],
      "reserve": null,
      "roster_id": 9,
      "settings": {
        "division": 1,
        "fpts": 367,
        "fpts_against": 314,
        "fpts_against_decimal": 65,
        "fpts_decimal": 70,
        "losses": 1,
        "ppts": 429,
        "ppts_decimal": 10,
        "ties": 0,
        "total_moves": 0,
        "waiver_budget_used": 0,
        "waiver_position": 3,
        "wins": 2
      },
      "starters": [
        "6804",
        "9221",
        "6813",
        "8112",
        "12514",
        "12518",
        "12507",
        "12711",
        "DET"
      ],
      "taxi": null
    },
    {
      "co_owners": null,
      "keepers": null,
      "league_id": "1257465328837861376",
      "metadata": {
        "record": "LWL",
        "streak": "1L"
      },
      "owner_id": "1122498641165492224",
      "player_map": null,
      "players": [
        "11566",
        "11604",
        "11624",
        "11635",
        "12892",
        "1945",
        "5095",
        "5870",
        "6768",
        "6783",
        "6790",
        "6794",
        "6806",
        "9226",
        "BUF"
      ],
      "reserve": [
        "12892"
      ],
      "roster_id": 10,
      "settings": {
        "division": 2,
        "fpts": 357,
        "fpts_against": 378,
        "fpts_against_decimal": 40,
        "fpts_decimal": 15,
        "losses": 2,
        "ppts": 376,
        "ppts_decimal": 45,
        "ties": 0,
        "total_moves": 0,
        "waiver_budget_used": 0,
        "waiver_position": 10,
        "wins": 1
      },
      "starters": [
        "5870",
        "9226",
        "6806",
        "6794",
        "11635",
        "11604",
        "6790",
        "5095",
        "BUF"
      ],
      "taxi": null
    }
  ],
  "week": 4,
  "matchups": [
    {
      "points": 25.95,
      "players": [
        "10236",
        "11577",
        "11620",
        "2747",
        "3321",
        "5844",
        "5859",
        "6797",
        "6801",
        "8137",
        "8151",
        "9509",
        "GB"
      ],
      "roster_id": 1,
      "custom_points": null,
      "matchup_id": 2,
      "starters": [
        "6797",
        "9509",
        "8151",
        "11620",
        "8137",
        "10236",
        "5859",
        "2747",
        "GB"
      ],
      "starters_points": [
        0.45,
        0.5,
        12,
        0,
        0,
        0,
        0,
        13,
        0
      ],
      "players_points": {
        "2747": 13,
        "3321": 0,
        "5844": 7.9,
        "5859": 0,
        "6797": 0.45,
        "6801": 0,
        "8137": 0,
        "8151": 12,
        "9509": 0.5,
        "10236": 0,
        "11577": 0,
        "11620": 0,
        "GB": 0
      }
    },
    {
      "points": 10.85,
      "players": [
        "11632",
        "11638",
        "11655",
        "12512",
        "12526",
        "12527",
        "3163",
        "4137",
        "4195",
        "4981",
        "5045",
        "7569",
        "9224",
        "9484",
        "ATL"
      ],
      "roster_id": 2,
      "custom_points": null,
      "matchup_id": 1,
      "starters": [
        "3163",
        "12527",
        "12512",
        "11632",
        "7569",
        "9484",
        "12526",
        "4195",
        "ATL"
      ],
      "starters_points": [
        0.85,
        0,
        0,
        0,
        0,
        0,
        0,
        0,
        10
      ],
      "players_points": {
        "3163": 0.85,
        "4137": 0,
        "4195": 0,
        "4981": 1.8,
        "5045": 0,
        "7569": 0,
        "9224": 0,
        "9484": 0,
        "11632": 0,
        "11638": 0,
        "11655": 0,
        "12512": 0,
        "12526": 0,
        "12527": 0,
        "ATL": 10
      }
    },
    {
      "points": 13,
      "players": [
        "10222",
        "11539",
        "11563",
        "12481",
        "2133",
        "5850",
        "5947",
        "6904",
        "7002",
        "7049",
        "7564",
        "8155",
        "9488",
        "9754",
        "DEN"
      ],
      "roster_id": 3,
      "custom_points": null,
      "matchup_id": 4,
      "starters": [
        "6904",
        "12481",
        "5850",
        "7564",
        "9488",
        "7002",
        "2133",
        "11539",
        "DEN"
      ],
      "starters_points": [
        0,
        0,
        0,
        0,
        13,
        0,
        0,
        0,
        0
      ],
      "players_points": {
        "2133": 0,
        "5850": 0,
        "5947": 0,
        "6904": 0,
        "7002": 0,
        "7049": 0,
        "7564": 0,
        "8155": 0,
        "9488": 13,
        "9754": 0,
        "10222": 0,
        "11539": 0,
        "11563": 0,
        "12481": 0,
        "DEN": 0
      }
    },
    {
      "points": 8.6,
      "players": [
        "11560",
        "3451",
        "4046",
        "4199",
        "5012",
        "5846",
        "5872",
        "7547",
        "7553",
        "7594",
        "8150",
        "9493",
        "9997",
        "MIN"
      ],
      "roster_id": 4,
      "custom_points": null,
      "matchup_id": 5,
      "starters": [
        "11560",
        "8150",
        "7594",
        "9493",
        "7547",
        "7553",
        "9997",
        "3451",
        "MIN"
      ],
      "starters_points": [
        0,
        0,
        0,
        0,
        0,
        3.6,
        0,
        0,
        5
      ],
      "players_points": {
        "3451": 0,
        "4046": 0,
        "4199": 0,
        "5012": 0,
        "5846": 23.6,
        "5872": 0,
        "7547": 0,
        "7553": 3.6,
        "7594": 0,
        "8150": 0,
        "9493": 0,
        "9997": 0,
        "11560": 0,
        "MIN": 5
      }
    },
    {
      "points": 33.1,
      "players": [
        "11533",
        "11589",
        "11631",
        "12506",
        "4035",
        "4984",
        "5849",
        "5892",
        "6786",
        "7588",
        "8130",
        "8144",
        "8408",
        "TB"
      ],
      "roster_id": 5,
      "custom_points": null,
      "matchup_id": 1,
      "starters": [
        "4984",
        "8408",
        "7588",
        "8144",
        "11631",
        "8130",
        "12506",
        "11533",
        "TB"
      ],
      "starters_points": [
        0.7,
        10.2,
        0,
        0,
        0,
        12.2,
        0,
        0,
        10
      ],
      "players_points": {
        "4035": 0,
        "4984": 0.7,
        "5849": 22.1,
        "5892": 0,
        "6786": 0,
        "7588": 0,
        "8130": 12.2,
        "8144": 0,
        "8408": 10.2,
        "11533": 0,
        "11589": 10.4,
        "11631": 0,
        "12506": 0,
        "TB": 10
      }
    },
    {
      "points": 12,
      "players": [
        "10213",
        "10859",
        "11564",
        "11584",
        "11628",
        "12489",
        "17",
        "3198",
        "4033",
        "4983",
        "6111",
        "6770",
        "6819",
        "8228",
        "PHI"
      ],
      "roster_id": 6,
      "custom_points": null,
      "matchup_id": 3,
      "starters": [
        "11564",
        "3198",
        "11584",
        "6819",
        "4983",
        "10859",
        "10213",
        "17",
        "PHI"
      ],
      "starters_points": [
        0,
        0,
        2,
        0,
        0,
        0,
        0,
        0,
        10
      ],
      "players_points": {
        "17": 0,
        "3198": 0,
        "4033": 0,
        "4983": 0,
        "6111": 0,
        "6770": 0,
        "6819": 0,
        "8228": 0,
        "10213": 0,
        "10859": 0,
        "11564": 0,
        "11584": 2,
        "11628": 18.6,
        "12489": 0,
        "PHI": 10
      }
    },
    {
      "points": 8.9,
      "players": [
        "12501",
        "1466",
        "1479",
        "3294",
        "4034",
        "4039",
        "4892",
        "5848",
        "5927",
        "5967",
        "7543",
        "8110",
        "8259",
        "KC"
      ],
      "roster_id": 7,
      "custom_points": null,
      "matchup_id": 5,
      "starters": [
        "4892",
        "4034",
        "7543",
        "5848",
        "1479",
        "8110",
        "4039",
        "8259",
        "KC"
      ],
      "starters_points": [
        0.4,
        0,
        0,
        0,
        1.9,
        0,
        6.6,
        0,
        0
      ],
      "players_points": {
        "1466": 0,
        "1479": 1.9,
        "3294": 0,
        "4034": 0,
        "4039": 6.6,
        "4892": 0.4,
        "5848": 0,
        "5927": 0,
        "5967": 0.3,
        "7543": 0,
        "8110": 0,
        "8259": 0,
        "12501": 0,
        "KC": 0
      }
    },
    {
      "points": 5.7,
      "players": [
        "12504",
        "12533",
        "1339",
        "4037",
        "4217",
        "4227",
        "4866",
        "4881",
        "7525",
        "7526",
        "8138",
        "8146",
        "8183",
        "ARI"
      ],
      "roster_id": 8,
      "custom_points": null,
      "matchup_id": 3,
      "starters": [
        "4881",
        "4866",
        "8138",
        "8146",
        "7525",
        "1339",
        "7526",
        "4227",
        "ARI"
      ],
      "starters_points": [
        0,
        0,
        0.7,
        0,
        0,
        0,
        0,
        0,
        5
      ],
      "players_points": {
        "1339": 0,
        "4037": 0,
        "4217": 0,
        "4227": 0,
        "4866": 0,
        "4881": 0,
        "7525": 0,
        "7526": 0,
        "8138": 0.7,
        "8146": 0,
        "8183": 0,
        "12504": 2.2,
        "12533": 0,
        "ARI": 5
      }
    },
    {
      "points": 11.6,
      "players": [
        "12507",
        "12514",
        "12518",
        "12529",
        "12530",
        "12711",
        "2216",
        "6804",
        "6813",
        "8112",
        "8148",
        "9221",
        "9494",
        "DET"
      ],
      "roster_id": 9,
      "custom_points": null,
      "matchup_id": 2,
      "starters": [
        "6804",
        "9221",
        "6813",
        "8112",
        "12514",
        "12518",
        "12507",
        "12711",
        "DET"
      ],
      "starters_points": [
        0,
        1.7,
        0,
        0,
        0,
        0,
        -0.1,
        0,
        10
      ],
      "players_points": {
        "2216": 0,
        "6804": 0,
        "6813": 0,
        "8112": 0,
        "8148": 2.3,
        "9221": 1.7,
        "9494": 0,
        "12507": -0.1,
        "12514": 0,
        "12518": 0,
        "12529": 0,
        "12530": 0,
        "12711": 0,
        "DET": 10
      }
    },
    {
      "points": 32.6,
      "players": [
        "11566",
        "11604",
        "11624",
        "11635",
        "12892",
        "1945",
        "5095",
        "5870",
        "6768",
        "6783",
        "6790",
        "6794",
        "6806",
        "9226",
        "BUF"
      ],
      "roster_id": 10,
      "custom_points": null,
      "matchup_id": 4,
      "starters": [
        "5870",
        "9226",
        "6806",
        "6794",
        "11635",
        "11604",
        "6790",
        "5095",
        "BUF"
      ],
      "starters_points": [
        0,
        0,
        0,
        22.6,
        0,
        0,
        0,
        0,
        10
      ],
      "players_points": {
        "1945": 5,
        "5095": 0,
        "5870": 0,
        "6768": 0,
        "6783": 0,
        "6790": 0,
        "6794": 22.6,
        "6806": 0,
        "9226": 0,
        "11566": 0,
        "11604": 0,
        "11624": 0,
        "11635": 0,
        "12892": 0,
        "BUF": 10
      }
    }
  ]
}